{"name":"k1_word_v100_regDotStar_m50","sourceObjs":"k1_word_v100","template":"\"function (so) {\\n    return {\\n        prop1: \\n          rog.randomReplaceWith(\\n                replaceRandomChars(\\n                    so.prop1,\\n                    '.*',\\n                    rog.getRandomInt(0,so.prop1.length)), \\n                randomChars3to10(), \\n                0.5)\\n      };  \\n    }\"","Date":"Fri Jan 22 2016 01:41:17 GMT+0000 (UTC)","objects":[{"prop1":"7QXqvC3s"},{"prop1":"ywCmqSZ"},{"prop1":"4.*Kx"},{"prop1":"kmin"},{"prop1":".*xByR"},{"prop1":"uGJNK"},{"prop1":"13rZ44oXl"},{"prop1":".*"},{"prop1":"FP6h"},{"prop1":"a.*fG"},{"prop1":"6AtkcYbfx8"},{"prop1":"A.*"},{"prop1":"8aTLY"},{"prop1":".*"},{"prop1":"Pi2Ur96WH"},{"prop1":"ncj6Et"},{"prop1":"IiUj56Q3Z"},{"prop1":"mt4QTCPp"},{"prop1":".*zlWfqJ"},{"prop1":"Gc1ctT8v"},{"prop1":"uBPR"},{"prop1":".*sj"},{"prop1":"7A1A"},{"prop1":"83yp"},{"prop1":"n.*X1fuR"},{"prop1":"OCV.*o"},{"prop1":"Sl.*q"},{"prop1":"u6m7uSNiKx"},{"prop1":"oi3cbW4yE"},{"prop1":"MeXVN"},{"prop1":"8I.*40IZI"},{"prop1":"S88r"},{"prop1":"sxg.*jsmzx"},{"prop1":"V9N.*"},{"prop1":"6Anqp4"},{"prop1":"GczYrU.*"},{"prop1":"sax"},{"prop1":"uBTlo75Nz"},{"prop1":"RJj3"},{"prop1":"t5a9v"},{"prop1":"Kf.*"},{"prop1":"V.*"},{"prop1":"oL0r.*e"},{"prop1":"5p.*"},{"prop1":"bqDsSpTvc.*"},{"prop1":".*"},{"prop1":"ltbGo8h"},{"prop1":"hHy0"},{"prop1":"2DL"},{"prop1":"7gW2f7Xrb6.*"},{"prop1":"lcL.*"},{"prop1":"rNH3kyQ62"},{"prop1":"aoF.*AKW4C"},{"prop1":"TFaN1"},{"prop1":"qcK.*"},{"prop1":"yJc.*H"},{"prop1":"WdNF.*Kh"},{"prop1":"bQf"},{"prop1":"e8CMWeN.*"},{"prop1":".*4t"},{"prop1":"2X.*d"},{"prop1":"Q.*Z02"},{"prop1":"vXQ"},{"prop1":"nm"},{"prop1":"cti"},{"prop1":"z7z2f6r"},{"prop1":"9.*"},{"prop1":".*Y"},{"prop1":"OQ.*"},{"prop1":"N.*"},{"prop1":"SUWN"},{"prop1":"ndngg"},{"prop1":"ws.*b"},{"prop1":"IvakPKH.*"},{"prop1":"J8w.*NnS"},{"prop1":"m.*"},{"prop1":"bp5"},{"prop1":"ot.*DxY"},{"prop1":".*RO"},{"prop1":"dabN"},{"prop1":"SnL"},{"prop1":"Tg0LfVl"},{"prop1":"MhLlJtqk"},{"prop1":"K0NFzc6"},{"prop1":"Dt2"},{"prop1":"n.*"},{"prop1":"5p9luUZL"},{"prop1":"sxgxIP"},{"prop1":"GGANcAF"},{"prop1":"oGKB"},{"prop1":"hurEb9CqP"},{"prop1":"ROd"},{"prop1":"iwGI9"},{"prop1":"FMeW"},{"prop1":"vlgA64gWM"},{"prop1":"69Ldee"},{"prop1":"tfzIF"},{"prop1":"3en"},{"prop1":"5T2Jx0NQZ"},{"prop1":"iuBXR"}]}